MANIFEST.in
setup.py
UW_RestClients.egg-info/PKG-INFO
UW_RestClients.egg-info/SOURCES.txt
UW_RestClients.egg-info/dependency_links.txt
UW_RestClients.egg-info/requires.txt
UW_RestClients.egg-info/top_level.txt
restclients/VERSION
restclients/__init__.py
restclients/amazon_sqs.py
restclients/bookstore.py
restclients/cache_implementation.py
restclients/cache_manager.py
restclients/dao.py
restclients/exceptions.py
restclients/gws.py
restclients/kws.py
restclients/middleware.py
restclients/mock_http.py
restclients/myplan.py
restclients/nws.py
restclients/pws.py
restclients/requirements.txt
restclients/sms.py
restclients/tests.py
restclients/thread.py
restclients/upass.py
restclients/urls.py
restclients/views.py
restclients/bridge/__init__.py
restclients/bridge/custom_field.py
restclients/bridge/user.py
restclients/canvas/__init__.py
restclients/canvas/accounts.py
restclients/canvas/admins.py
restclients/canvas/analytics.py
restclients/canvas/assignments.py
restclients/canvas/authentications.py
restclients/canvas/conversations.py
restclients/canvas/courses.py
restclients/canvas/discussions.py
restclients/canvas/enrollments.py
restclients/canvas/external_tools.py
restclients/canvas/grading_standards.py
restclients/canvas/groups.py
restclients/canvas/page_views.py
restclients/canvas/quizzes.py
restclients/canvas/reports.py
restclients/canvas/roles.py
restclients/canvas/sections.py
restclients/canvas/sis_import.py
restclients/canvas/submissions.py
restclients/canvas/terms.py
restclients/canvas/users.py
restclients/catalyst/__init__.py
restclients/catalyst/gradebook.py
restclients/dao_implementation/__init__.py
restclients/dao_implementation/amazon_sqs.py
restclients/dao_implementation/book.py
restclients/dao_implementation/bridge.py
restclients/dao_implementation/canvas.py
restclients/dao_implementation/catalyst.py
restclients/dao_implementation/errors.py
restclients/dao_implementation/grad.py
restclients/dao_implementation/gws.py
restclients/dao_implementation/hfs.py
restclients/dao_implementation/hrpws.py
restclients/dao_implementation/iasystem.py
restclients/dao_implementation/kws.py
restclients/dao_implementation/live.py
