Metadata-Version: 1.1
Name: UW-RestClients
Version: 2.2
Summary: Clients for a variety of RESTful web services at the University of Washington
Home-page: https://github.com/uw-it-aca/uw-restclients
Author: UW-IT AXDD
Author-email: aca-it@uw.edu
License: Apache License, Version 2.0
Platform: UNKNOWN
Classifier: Intended Audience :: Developers
Classifier: License :: OSI Approved :: Apache Software License
Classifier: Operating System :: OS Independent
Classifier: Programming Language :: Python
Classifier: Programming Language :: Python :: 2.7
Classifier: Programming Language :: Python :: 3.4
